{
  "name": "Hotel Les Arcades",
  "address": {
    "city": "Knokke-Zoute",
    "street": "Elizabetlaan 50"
  },
  "availableServices": {
    "breakfast": {
      "categories": [
        {
          "category": "DRINK",
          "items": [
            {
              "price": {
                "currency": "€",
                "value": "0.5"
              },
              "available": true,
              "name": "Expresso"
            },
            {
              "price": {
                "currency": "€",
                "value": "3"
              },
              "available": true,
              "name": "Hot chocolate"
            }
          ]
        },
        {
          "category": "DISH",
          "items": [
            {
              "price": {
                "currency": "€",
                "value": "2"
              },
              "available": true,
              "name": "Toasts with jam"
            },
            {
              "price": {
                "currency": "€",
                "value": "3.5"
              },
              "available": true,
              "name": "Scrambled eggs"
            }
          ]
        }
      ],
      "fromHour": "16-12-2016 09:00:00",
      "price": {
        "currency": "€",
        "value": 5
      },
      "toHour": "16-09-2016 11:00:00",
      "description": ""
    },
    "roomService": {
      "categories": [
        {
          "category": "DRINK",
          "items": [
            {
              "price": {
                "currency": "€",
                "value": "2"
              },
              "available": true,
              "name": "Beer"
            }
          ]
        },
        {
          "category": "SNACK",
          "items": [
            {
              "price": {
                "currency": "€",
                "value": "1.5"
              },
              "available": true,
              "name": "Ice cream"
            }
          ]
        }
      ],
      "price": {
        "currency": "€",
        "value": 4
      },
      "description": ""
    },
    "carPark": {
      "price": {
        "currency": "€",
        "value": 3
      },
      "description": ""
    },
    "housekeeping": {
      "items": [
        {
          "name": "Towels"
        },
        {
          "name": "Toilet paper"
        }
      ],
      "price": {
        "text": "Free"
      },
      "description": ""
    },
    "receptionCall": {
      "price": {
        "text": ""
      },
      "phoneNumber": "+32 50 60 10 73"
    },
    "spa": {
      "items": [
        {
          "calendar": {
            "days": []
          },
          "price": {
            "currency": "€",
            "value": 3
          },
          "name": "Thai massage"
        },
        {
          "calendar": {
            "days": []
          },
          "price": {
            "currency": "€",
            "value": 5
          },
          "name": "Manicure"
        }
      ],
      "price": {
        "currency": "€",
        "value": 5
      },
      "description": ""
    },
    "petCare": {
      "items": [],
      "price": {
        "currency": "€",
        "value": 7
      },
      "description": ""
    },
    "taxi": {
      "items": [
        {
          "name": "Radio Taxi",
          "number": "390-035-5524"
        },
        {
          "name": "Blue Taxi 24",
          "number": "328-004-4540"
        }
      ],
      "price": {
        "text": "Free"
      }
    }
  },
  "usefulInformation": {
    "wifiPassword": "erir9732f9fwdres",
    "items": [
      {
        "name": "Check-in",
        "fromHour": "16-12-2016 08:00:00",
        "toHour": "16-12-2016 08:00:00"
      },
      {
        "name": "Check-out",
        "fromHour": "16-12-2016 20:00:00",
        "toHour": "16-12-2016 20:00:00"
      }
    ]
  },
  "roomDirectory": {
    "sections": [
      {
          "heading": "Towels",
          "text": "Some information about the towels"
      },
      {
          "heading": "Toilet paper",
          "text": "Some information about the toilet paper"
      }
    ]
  },
  "galleries": [
    {
      "type": "MAIN",
      "links": [
        "https://a1.cdn-hotels.com/landing/images/2ddeb5d1-8fa5-4d55-b78d-62e5b0d208bf_20130621092935.jpg",
        "http://static1.squarespace.com/static/512f9596e4b0ed945e3306aa/t/513e39c7e4b0517c723271a8/1363032525439/IMG_4536+copy.JPG"
      ]
    }
  ]
}